openmsimodel/__init__.py
openmsimodel/db/__init__.py
openmsimodel/db/gemd_database.py
openmsimodel/db/open_db.py
openmsimodel/db/queries.py
openmsimodel/entity/__init__.py
openmsimodel/entity/element.py
openmsimodel/entity/gemd/__init__.py
openmsimodel/entity/gemd/gemd_element.py
openmsimodel/entity/gemd/helpers.py
openmsimodel/entity/gemd/impl.py
openmsimodel/entity/gemd/ingredient.py
openmsimodel/entity/gemd/material.py
openmsimodel/entity/gemd/measurement.py
openmsimodel/entity/gemd/process.py
openmsimodel/entity/gemd/process_or_measurement.py
openmsimodel/entity/gemd/ingredients/__init__.py
openmsimodel/entity/gemd/materials/__init__.py
openmsimodel/entity/gemd/materials/birdshot/__init__.py
openmsimodel/entity/gemd/materials/birdshot/alloy.py
openmsimodel/entity/gemd/materials/birdshot/composition.py
openmsimodel/entity/gemd/materials/birdshot/element.py
openmsimodel/entity/gemd/materials/birdshot/inferred_alloy_compositions.py
openmsimodel/entity/gemd/materials/birdshot/summary.py
openmsimodel/entity/gemd/materials/birdshot/traveler.py
openmsimodel/entity/gemd/materials/birdshot/traveler_sample.py
openmsimodel/entity/gemd/materials/birdshot/traveler_samples.py
openmsimodel/entity/gemd/measurements/__init__.py
openmsimodel/entity/gemd/measurements/birdshot/__init__.py
openmsimodel/entity/gemd/measurements/birdshot/measure_dimensions.py
openmsimodel/entity/gemd/measurements/birdshot/mounting_and_polishing.py
openmsimodel/entity/gemd/measurements/birdshot/ni.py
openmsimodel/entity/gemd/measurements/birdshot/sem.py
openmsimodel/entity/gemd/measurements/birdshot/srjt.py
openmsimodel/entity/gemd/measurements/birdshot/tensile.py
openmsimodel/entity/gemd/measurements/birdshot/weighting.py
openmsimodel/entity/gemd/measurements/birdshot/xrd.py
openmsimodel/entity/gemd/processes/__init__.py
openmsimodel/entity/gemd/processes/birdshot/__init__.py
openmsimodel/entity/gemd/processes/birdshot/add_material.py
openmsimodel-0.1.6.dist-info/METADATA
openmsimodel-0.1.6.dist-info/WHEEL
openmsimodel-0.1.6.dist-info/entry_points.txt
openmsimodel-0.1.6.dist-info/top_level.txt
openmsimodel-0.1.6.dist-info/RECORD
